QEPPI/QEPPI.py
QEPPI/__init__.py
QEPPI/constant.py
QEPPI/util.py
QEPPI/version.py
qeppicommunity-0.1.21.dist-info/licenses/LICENSE
qeppicommunity-0.1.21.dist-info/METADATA
qeppicommunity-0.1.21.dist-info/WHEEL
qeppicommunity-0.1.21.dist-info/top_level.txt
qeppicommunity-0.1.21.dist-info/RECORD
